boulderopalscaleup/__init__.py
boulderopalscaleup/auth.py
boulderopalscaleup/client.py
boulderopalscaleup/common.py
boulderopalscaleup/constants.py
boulderopalscaleup/controllers/__init__.py
boulderopalscaleup/controllers/_base.py
boulderopalscaleup/controllers/qblox.py
boulderopalscaleup/controllers/quantum_machines/__init__.py
boulderopalscaleup/controllers/quantum_machines/opx.py
boulderopalscaleup/controllers/quantum_machines/opx1000.py
boulderopalscaleup/device.py
boulderopalscaleup/experiments.py
boulderopalscaleup/plots.py
boulderopalscaleup/py.typed
boulderopalscaleup/qblox.py
boulderopalscaleup/routines.py
boulderopalscaleup/utils.py
boulderopalscaleup/version.py
boulder_opal_scale_up-1.0.15.dist-info/LICENSE
boulder_opal_scale_up-1.0.15.dist-info/METADATA
boulder_opal_scale_up-1.0.15.dist-info/WHEEL
boulder_opal_scale_up-1.0.15.dist-info/RECORD
